torchsplit/__init__.py
torchsplit/split.py
torchsplit-0.0.8.dist-info/LICENSE
torchsplit-0.0.8.dist-info/METADATA
torchsplit-0.0.8.dist-info/WHEEL
torchsplit-0.0.8.dist-info/top_level.txt
torchsplit-0.0.8.dist-info/RECORD
