Metadata-Version: 2.1
Name: torchsplit
Version: 0.0.8
Summary: A basic implementation to split labled data
Home-page: https://github.com/Gorluxor/torchsplit
Author: Aleksandar Cvejic
Author-email: cvejicaca@gmail.com
License: MIT
Keywords: split,dataset,into,test,validation
Platform: UNKNOWN
Classifier: License :: OSI Approved :: BSD License
Classifier: Programming Language :: Python :: 3.7
Requires-Dist: scikit-learn
Requires-Dist: torch
Requires-Dist: numpy
Requires-Dist: torchvision
